{
    "Link": "https://glints.com/vn/opportunities/jobs/tester/e702fe92-ccb5-4417-95ab-038418a0c2da?utm_referrer=explore&traceInfo=e5d079aef9f000b01086b4edbafae9f3",
    "Title": "Tester",
    "Salary": [
        "₫ 6-10 Tr/Tháng"
    ],
    "Location": "Quận Cầu Giấy, Hà Nội  ·  Làm tại công ty  ·  Việc làm fulltime",
    "Last_updated": "Cập nhật 20 ngày trước",
    "Created_time": "01-09-2024 13:26:58",
    "Skills": [
        "Manual Testing",
        "Software Testing",
        "test casE"
    ],
    "Requirement": [
        "1 - 3 năm kinh nghiệm",
        "Tối thiểu Cử Nhân"
    ],
    "Hirer": "tabtab .me",
    "Company": "Nhà tuyển dụng · Tabtab Vietnam",
    "Company_link": "https://glints.com/vn/companies/tabtab-vietnam/1ce9f11f-2aa5-42c7-89dc-69c09f07c2f3",
    "Company_location": "36/45 Trần Thái Tông, Quận Cầu Giấy",
    "Category": [
        "Computer & Information Technology",
        "QA Tester, Quality Assurance Tester"
    ]
}