{
    "Link": "https://glints.com/vn/opportunities/jobs/sales-trainee/efd9c1b4-133d-4c61-83da-743884a343d3?utm_referrer=explore&traceInfo=3013167b4b06c7e400d909f5eac50a4f",
    "Title": "Sales Trainee",
    "Salary": [
        "₫ 8-10 Tr/Tháng"
    ],
    "Location": "Quận Thủ Đức, Thành phố Hồ Chí Minh  ·  Làm tại công ty  ·  Việc làm fulltime",
    "Last_updated": "Cập nhật Hôm qua",
    "Created_time": "29-08-2024 22:47:32",
    "Skills": [
        "Customer Support",
        "Telesales",
        "B2C Sales"
    ],
    "Requirement": [
        "Dưới một năm kinh nghiệm",
        "Tối thiểu Cao Đẳng",
        "22-25 tuổi"
    ],
    "Hirer": "Phuong VU",
    "Company": "Nhà tuyển dụng · Công ty CP Eduvator",
    "Company_link": "https://glints.com/vn/companies/cong-ty-cp-eduvator/747eacfe-3b42-4d18-81b9-84efc48988be",
    "Company_location": "308 Trần Phú, P.8, Quận 5, TP.HCM",
    "Category": [
        "Giáo Dục Đào Tạo",
        "Tư Vấn Giáo Dục"
    ]
}